snapshot_integration_package/DISCLAIMER
snapshot_integration_package/EULA
snapshot_integration_package/__init__.py
snapshot_integration_package/semiauto_main.cp39-win32.pyd
snapshot_integration_package/semiauto_misc.cp39-win32.pyd
snapshot_integration_package/semiauto_ps.cp39-win32.pyd
snapshot_integration_package/semiauto_rc.cp39-win32.pyd
snapshot_integration_package-1.0.6.dist-info/licenses/LICENSE
snapshot_integration_package-1.0.6.dist-info/METADATA
snapshot_integration_package-1.0.6.dist-info/WHEEL
snapshot_integration_package-1.0.6.dist-info/top_level.txt
snapshot_integration_package-1.0.6.dist-info/RECORD
