Metadata-Version: 2.4
Name: snapshot_integration_package
Version: 1.0.6
Summary: This package is useful for PSS®E power system assessment.
Home-page: https://
Author: Varchas Solutions Pty Ltd
Author-email: Pritesh Patel <pritesh.patel@varchassolutions.com.au>
License: Proprietary
Requires-Python: >=3.9,<3.12
License-File: LICENSE
Requires-Dist: numpy==1.21.6
Requires-Dist: pandas>=1.5.3
Requires-Dist: requests>=2.32.3
Requires-Dist: openpyxl>=3.1.5
Dynamic: author
Dynamic: home-page
Dynamic: license-file
Dynamic: requires-python
